outlier/__init__.py
outlier/outlier.py
outlier_101703396-1.2.3.dist-info/LICENSE.txt
outlier_101703396-1.2.3.dist-info/METADATA
outlier_101703396-1.2.3.dist-info/WHEEL
outlier_101703396-1.2.3.dist-info/top_level.txt
outlier_101703396-1.2.3.dist-info/RECORD
