Metadata-Version: 2.1
Name: outlier-101703396
Version: 1.2.3
Summary: Outlier Remover tool
Home-page: UNKNOWN
Author: Prakhar Shukla
Author-email: pshukla_be17@thapar.edu
License: UNKNOWN
Platform: UNKNOWN
Classifier: Programming Language :: Python :: 3
Classifier: License :: OSI Approved :: MIT License
Classifier: Operating System :: OS Independent
Requires-Python: >=3.6
